SolarGUI/__init__.py
SolarGUI/cel__CONSTANTS.py
SolarGUI/cel__moons.py
SolarGUI/cel__object.py
SolarGUI/cel__others.py
SolarGUI/cel__planets.py
SolarGUI/cel__stars.py
SolarGUI/show_celestial_object.py
SolarGUI/solar_gui.py
SolarGUI/tk_functions.py
SolarGUI/utilities.py
"SolarGUI/images/earth/2335_earthmars_med : Earth and Moon as seen from Martian surface by Curiosity rover ~ NASA, JPL-Caltech, TAMU.jpg"
SolarGUI/images/earth/Apollo10ViewofEarth : View of Earth captured by Apollo 10 spacecraft ~ NASA.jpg
SolarGUI/images/earth/CrescentEarth : Cresent view of Earth captured by Apollo 17 mission ~ NASA.jpg
"SolarGUI/images/earth/PIA13227 : Mosaic of Earths' images taken from the Moon using Lunar Reconnaissance Orbiter Camera ~ NASA, GSFC, Arizona State University.jpg"
SolarGUI/images/earth/as11-44-6549_orig : Image of Earth captured by Apollo 11 spacecraft in July 1969 ~ NASA.jpg
"SolarGUI/images/jupiter/13051_PIA07783 : A mosaic of images from Cassini spacecraft images showing the north pole view of Jupiter using cylindrical and polar stereographic projections ~ NASA, JPL, Space Science Institute.jpg"
"SolarGUI/images/jupiter/13054_PIA07784 : 13051_PIA07783 : A mosaic of images from Cassini spacecraft images showing the sourth pole view of Jupiter ~ NASA, JPL, Space Science Institute.jpg"
"SolarGUI/images/jupiter/192016main_100907_11 : New Horizon's view of Jupiter and one of its moons (Io) taken during the flyby in 2007 ~ NASA, JHUAPL.jpg"
"SolarGUI/images/jupiter/2486_stsci-h-p1936a_1800 : June 2019 image of Jupiter by the HST showing the spectacular cloud patterns ~ NASA, ESA, A. Simon (GSFC), and M. H. Wong (University of California, Berkeley).jpg"
SolarGUI/images/jupiter/739470main_jup_74hc680_0 : Jupiter as seen by Pioneer 11 spacecraft from the North pole of Jupiter ~ NASA Ames.jpg
"SolarGUI/images/jupiter/P44431Ac : Impact of fragmented Shoemaker Levy 9 comet hitting the Jovian giant planet. Image taken on July 1994 ~ HST Comet Team, NASA.jpg"
SolarGUI-0.1.6.dist-info/LICENSE
SolarGUI-0.1.6.dist-info/METADATA
SolarGUI-0.1.6.dist-info/WHEEL
SolarGUI-0.1.6.dist-info/entry_points.txt
SolarGUI-0.1.6.dist-info/top_level.txt
SolarGUI-0.1.6.dist-info/RECORD
