Metadata-Version: 2.1
Name: SolarGUI
Version: 0.1.6
Summary: A program which contains information about the solar system planets, moon, pluto, Sun, and more.
Home-page: https://github.com/AstrophysicsAndPython/SolarGUI
Author: Astrophysics and Python, Syed Ali Mohsin Bukhari
Author-email: astrophysicsandpython@gmail.com, syedali.b@outlook.com
License: MIT
Classifier: License :: OSI Approved :: MIT License
Classifier: Programming Language :: Python :: 3.7
Classifier: Programming Language :: Python :: 3.8
Classifier: Programming Language :: Python :: 3.9
Requires-Python: >=3.7.*, <3.10.*
License-File: LICENSE
Requires-Dist: astropy (>=4.3.1)
Requires-Dist: numpy (>=1.21.6)
Requires-Dist: setuptools (>=59.6.0)
Requires-Dist: pillow (>=9.1.1)
